{
  "adult": false,
  "also_known_as": [
    "石田 彰",
    "いしだ あきら",
    "이시다 아키라",
    "آکیرا ایشیدا"
  ],
  "biography": "Akira Ishida (石田 彰, Ishida Akira, November 2, 1967) is a Japanese voice actor and actor from Nisshin, Aichi. He is affiliated with Peerless Gerbera.\n\nVoted the most popular voice actor in the Animage Anime Grand Prix in 2004, and the Best Supporting Actor at the 1st Seiyū Awards in 2007.",
  "birthday": "1967-11-02",
  "deathday": null,
  "gender": 2,
  "homepage": "http://pg-wcf.co.jp/profile/01",
  "id": 81244,
  "imdb_id": "nm0410907",
  "known_for_department": "Acting",
  "name": "Akira Ishida",
  "place_of_birth": "Nisshin, Aichi, Japan",
  "popularity": 3.4148,
  "profile_path": "/jnW2Gn2NlR2uwOCeyOuzypnTmkH.jpg",
  "external_ids": {
    "freebase_mid": "/m/02h8hr",
    "freebase_id": "/en/akira_ishida",
    "imdb_id": "nm0410907",
    "tvrage_id": 17582,
    "wikidata_id": "Q418736",
    "facebook_id": null,
    "instagram_id": null,
    "tiktok_id": null,
    "twitter_id": null,
    "youtube_id": null
  }
}