{
  "adult": false,
  "also_known_as": [
    "Radio Silence"
  ],
  "biography": "",
  "birthday": "1982-03-06",
  "deathday": null,
  "gender": 2,
  "homepage": null,
  "id": 1039527,
  "imdb_id": "nm2419470",
  "known_for_department": "Directing",
  "name": "Тайлер Джиллетт",
  "place_of_birth": "Flagstaff, Arizona, USA",
  "popularity": 1.1967,
  "profile_path": "/8R3iddOdFcvMXzeBVdTVALmm0CG.jpg",
  "external_ids": {
    "freebase_mid": null,
    "freebase_id": null,
    "imdb_id": "nm2419470",
    "tvrage_id": null,
    "wikidata_id": "Q16221753",
    "facebook_id": null,
    "instagram_id": null,
    "tiktok_id": null,
    "twitter_id": null,
    "youtube_id": null
  }
}