{
  "adult": false,
  "also_known_as": [
    "Mary Louise Streep"
  ],
  "biography": "💥Мэри Луиз Стрип. Родилась в 1949-ом году в Саммите, Нью-Джерси, США. Росла в семье с 2-мя младшими братьями. Отец работал руководителем фармацевтической компании, а мать была художницей. Училась в Йельской школе драмы. Работает актрисой и продюсером. С 1978-го замужем за скульптором Доном Гаммером, у пары 4-ро детей: сын Генри и дочери Мэми, Грейс и Луиза\n\n🏆Главные награды🏆: Оскар (1980) [Крамер против Крамера], Оскар (1983) [Выбор Софи], Оскар (2012) [Железная леди], BAFTA (2012) [Железная леди]\n\n🎬Главные проекты🎬: «Крамер против Крамера» (1979), «Выбор Софи» (1982), «Железная леди» (2011), «Дьявол носит Prada» (2006)\n\n⭐Интересный факт⭐: Мэрил известна своей феноменальной способностью менять акценты и голоса, она может говорить с точностью до нюансов любого диалекта",
  "birthday": "1949-06-22",
  "deathday": null,
  "gender": 1,
  "homepage": null,
  "id": 5064,
  "imdb_id": "nm0000658",
  "known_for_department": "Acting",
  "name": "Мэрил Стрип",
  "place_of_birth": "Summit, New Jersey, USA",
  "popularity": 11.2874,
  "profile_path": "/g5cVxQBAQ3AXt3LhdBXtbbN47Uc.jpg",
  "external_ids": {
    "freebase_mid": "/m/0h0wc",
    "freebase_id": "/en/meryl_streep",
    "imdb_id": "nm0000658",
    "tvrage_id": 59779,
    "wikidata_id": "Q873",
    "facebook_id": null,
    "instagram_id": null,
    "tiktok_id": null,
    "twitter_id": null,
    "youtube_id": null
  }
}