{
  "adult": false,
  "also_known_as": [
    "張軒睿",
    "张轩睿",
    "Чжан Сюань Жуй",
    "Xuan-Rui Zhang"
  ],
  "biography": "",
  "birthday": "1992-12-17",
  "deathday": null,
  "gender": 2,
  "homepage": null,
  "id": 1671345,
  "imdb_id": "nm6688102",
  "known_for_department": "Acting",
  "name": "Derek Chang",
  "place_of_birth": "Taipei, Taiwan",
  "popularity": 1.2533,
  "profile_path": "/lPvtlGroAk9BqrpibYNQd9DSdGI.jpg",
  "external_ids": {
    "freebase_mid": null,
    "freebase_id": null,
    "imdb_id": "nm6688102",
    "tvrage_id": null,
    "wikidata_id": "Q27888798",
    "facebook_id": "derekchang1217",
    "instagram_id": "derekctor",
    "tiktok_id": null,
    "twitter_id": null,
    "youtube_id": null
  }
}