{
  "adult": false,
  "also_known_as": [],
  "biography": "Craig Gillespie (born September 1 1967) is an Australian-American film, television, music video, and commercial director. He is best known for directing the films Lars and the Real Girl (2007), Fright Night (2011), I, Tonya (2017), and Cruella (2021).",
  "birthday": "1967-09-01",
  "deathday": null,
  "gender": 2,
  "homepage": null,
  "id": 50767,
  "imdb_id": "nm0318916",
  "known_for_department": "Directing",
  "name": "Craig Gillespie",
  "place_of_birth": "Sydney, New South Wales, Australia",
  "popularity": 1.8084,
  "profile_path": "/pVHspL9QWsXCm3t3VXEaCJ9y8Zz.jpg",
  "external_ids": {
    "freebase_mid": "/m/04jnwm9",
    "freebase_id": null,
    "imdb_id": "nm0318916",
    "tvrage_id": null,
    "wikidata_id": "Q3696452",
    "facebook_id": null,
    "instagram_id": null,
    "tiktok_id": null,
    "twitter_id": null,
    "youtube_id": null
  }
}