{
  "adult": false,
  "also_known_as": [
    "Andrei Tarkovskiy",
    "Андрей Тарковский",
    "Andrej Tarkovskij",
    "Andrei Tarkovski",
    "安德烈·塔尔科夫斯基",
    "أندري تاركوفسكي",
    "アンドレイ・タルコフスキー",
    "안드레이 타르콥스키",
    "Andrei Tarkovskij",
    "Andrey Arsenyevich Tarkovsky",
    "Andrey A. Tarkovsky",
    "Андрей Арсеньевич Тарковский",
    "Andrey Tarkovsky",
    "آندری تارکوفسکی",
    "安德烈·塔可夫斯基",
    "안드레이 타르코프스키",
    "אנדרי טרקובסקי",
    "Andriej Tarkowski",
    "Andreï Arsenievitch Tarkovski",
    "А. Тарковский"
  ],
  "biography": "Режиссёр, сценарист, актёр, художник.\n\nЗаслуженный деятель искусств РСФСР (1974). Народный артист РСФСР (1980).\n\nРодился в селе Завражье, Юрьевецкий район, Ивановская Промышленная область.\n\nУчился в Московском институте востоковедения, работал в геологических партиях. В 1960 году окончил режиссёрский факультет ВГИКа (мастерская М. И. Ромма) и защитил диплом короткометражным фильмом «Каток и скрипка» (1960, главный приз фестиваля студенческих фильмов в Нью‑Йорке, США, 1961).\n\nС 1961 года — режиссёр «Мосфильма». «Иваново детство» (1962, «Золотой лев святого Марка» на кинофестивале в Венеции, 1962 год и более 10 призов на других кинофестивалях) сделало имя Тарковского знаменитым.\n\nКартина «Страсти по Андрею» (1966, приз на кинофестивале в Канне, 1969), включенная в список 100 лучших фильмов в истории кино (1978), подверглась сокращениям и вышла на экраны в 1971 году под названием «Андрей Рублёв». Жизнь великого иконописца стала отправной точкой для размышлений о судьбе художника в России.\n\nВ «Солярисе» (1972, по роману Станислава Лема, «Серебряная пальмовая ветвь» и приз экуменического жюри на кинофестивале в Канне, 1972) Тарковский обращает свой взгляд в будущее, чтобы обнаружить в нем непреложные ценности бытия.\n\n«Зеркало» (1975) — автобиографический фильм, построенный на воспоминаниях о детстве, матери и отце — замечательном поэте Арсении Тарковском, чьи стихи звучат за кадром.\n\nВ 1977 году Тарковский ставит «Гамлета» Уильяма Шекспира в Московском Театре имени Ленинского комсомола (постановка успеха не имела).\n\nВ «Сталкере» (1979, по роману братьев Стругацких «Пикник на обочине», премия экуменического жюри кинофестиваля в Канне, 1982). Фильм‑путешествие в пространство человеческой души.\n\nВ 1982 году Андрей Тарковский уезжает в Италию, где в процессе поисков натуры для нового фильма снимает документальную ленту «Время путешествия» (1982). В 1983 году осуществляет постановку оперы «Борис Годунов» в Ковент‑гардене (Лондон).\n\n«Ностальгия» (1983, Италия‑Франция, Гран‑при, приз экуменического жюри на кинофестивале в Канне, 1983) рассказывает о русском поэте, умершем в Италии от тоски по Родине.\n\n«Жертвоприношение» (1986, специальная премия, премия экуменического жюри на кинофестивале в Канне, 1986), снятом в Швеции и ставшим последним фильмом Тарковского, его завещанием.\n\nПоследний фильм стал логической точкой в напряженном богоискательстве, пронизавшем всё творчество Тарковского.\n\nВ конце 1985 года режиссёру поставлен диагноз — рак лёгких. В январе 1986 года он начинает лечение в Париже, где 29 декабря 1986 года умирает на 55‑м году жизни. Похороны режиссёра состоялись 3 января 1987 года на Русском кладбище Сент‑Женевьев‑де‑Буа в окрестностях Парижа. Его надгробный памятник с надписью «человеку, который увидел ангела» был сделан Эрнстом Неизвестным.\n\nС 6 по 13 июля 2007 года в Ивановской области прошел I Международный кинофестиваль имени Андрея Тарковского «Зеркало». Кинофестиваль был посвящен 75‑летию со дня рождения Мастера.",
  "birthday": "1932-04-04",
  "deathday": "1986-12-29",
  "gender": 2,
  "homepage": null,
  "id": 8452,
  "imdb_id": "nm0001789",
  "known_for_department": "Directing",
  "name": "Андрей Тарковский",
  "place_of_birth": "Zavrazhye, USSR",
  "popularity": 1.4184,
  "profile_path": "/mytn9s5kc6CqzKZtbuJ73oA6ujy.jpg",
  "external_ids": {
    "freebase_mid": "/m/0hy8",
    "freebase_id": null,
    "imdb_id": "nm0001789",
    "tvrage_id": null,
    "wikidata_id": "Q853",
    "facebook_id": null,
    "instagram_id": null,
    "tiktok_id": null,
    "twitter_id": null,
    "youtube_id": null
  }
}