{
  "adult": false,
  "also_known_as": [
    "Kate McKinnon Berthold",
    "Kathryn McKinnon Berthold"
  ],
  "biography": "💥Кэтрин Маккиннон Бертольд. Родилась в 1984-ом году в Си-Клиффе, Нью-Йорк, США. Росла в семье с младшей сестрой. Отец работал архитектором, а мать была учительницей. Училась в Колумбийском университете в Нью-Йорке. Работает актрисой, комедианткой, сценаристкой и продюсером. Кейт открытая лесбиянка, но личную жизнь предпочитает держать в тайне\n\n🏆Главные награды🏆: Эмми (2016, 2017) [Saturday Night Live]\n\n🎬Главные проекты🎬: «Saturday Night Live» (2012), «Охотники за привидениями» (2016), «Супруги Роуз» (2025), «Шпион, который меня кинул» (2018), «Барби» (2023)\n\n⭐Интересный факт⭐: Кейт играет на 3 инструментах: виолончели, пианино и гитаре",
  "birthday": "1984-01-06",
  "deathday": null,
  "gender": 1,
  "homepage": null,
  "id": 1240487,
  "imdb_id": "nm0571952",
  "known_for_department": "Acting",
  "name": "Кейт Маккиннон",
  "place_of_birth": "Sea Cliff, New York, USA",
  "popularity": 2.2577,
  "profile_path": "/2cNetzianFcxPQbyOQnkAIkKUZE.jpg",
  "external_ids": {
    "freebase_mid": "/m/03qcvwn",
    "freebase_id": "/en/kate_mckinnon",
    "imdb_id": "nm0571952",
    "tvrage_id": 231130,
    "wikidata_id": "Q723057",
    "facebook_id": null,
    "instagram_id": null,
    "tiktok_id": null,
    "twitter_id": null,
    "youtube_id": null
  }
}