{
  "adult": false,
  "also_known_as": [],
  "biography": "",
  "birthday": "1979-04-12",
  "deathday": null,
  "gender": 2,
  "homepage": null,
  "id": 557210,
  "imdb_id": "nm2349060",
  "known_for_department": "Directing",
  "name": "Bejoy Nambiar",
  "place_of_birth": "Kannur, Kerala, India",
  "popularity": 0.4469,
  "profile_path": "/9tR68VDZc9XNX8wqGMymmTYnAxN.jpg",
  "external_ids": {
    "freebase_mid": null,
    "freebase_id": null,
    "imdb_id": "nm2349060",
    "tvrage_id": null,
    "wikidata_id": "Q4881554",
    "facebook_id": null,
    "instagram_id": "bejoynambiar",
    "tiktok_id": null,
    "twitter_id": "nambiarbejoy",
    "youtube_id": null
  }
}