{
  "adult": true,
  "also_known_as": [
    "Michelle Toomey ",
    "Michelle Elizabeth Toomey"
  ],
  "biography": "",
  "birthday": "1994-07-12",
  "deathday": null,
  "gender": 1,
  "homepage": null,
  "id": 2064657,
  "imdb_id": "nm7078228",
  "known_for_department": "Acting",
  "name": "Brooklyn Daniels",
  "place_of_birth": "Las Vegas, Nevada, USA",
  "popularity": 0.0,
  "profile_path": "/gXk3TqDhW3lnGpkYBSxgthbuUt5.jpg",
  "external_ids": {
    "freebase_mid": null,
    "freebase_id": null,
    "imdb_id": "nm7078228",
    "tvrage_id": null,
    "wikidata_id": null,
    "facebook_id": null,
    "instagram_id": null,
    "tiktok_id": null,
    "twitter_id": null,
    "youtube_id": null
  }
}