{
  "adult": false,
  "also_known_as": [],
  "biography": "",
  "birthday": "1955-12-06",
  "deathday": null,
  "gender": 2,
  "homepage": null,
  "id": 3214,
  "imdb_id": "nm0942833",
  "known_for_department": "Acting",
  "name": "Стивен Райт",
  "place_of_birth": "New York City, New York, USA",
  "popularity": 1.4907,
  "profile_path": "/9Q9buDjfm6uq0VE86MZ01o96lyG.jpg",
  "external_ids": {
    "freebase_mid": "/m/0q9t7",
    "freebase_id": "/en/steven_wright",
    "imdb_id": "nm0942833",
    "tvrage_id": 10546,
    "wikidata_id": "Q1969967",
    "facebook_id": null,
    "instagram_id": null,
    "tiktok_id": null,
    "twitter_id": null,
    "youtube_id": null
  }
}