{
  "adult": false,
  "also_known_as": [
    "Scarlett Brielle Spears"
  ],
  "biography": "",
  "birthday": "2017-06-12",
  "deathday": null,
  "gender": 1,
  "homepage": null,
  "id": 5374940,
  "imdb_id": "nm14198369",
  "known_for_department": "Acting",
  "name": "Скарлетт Спирс",
  "place_of_birth": null,
  "popularity": 0.3306,
  "profile_path": "/7hms2f7XA4eGd7p8st5jok2iwSe.jpg",
  "external_ids": {
    "freebase_mid": null,
    "freebase_id": null,
    "imdb_id": "nm14198369",
    "tvrage_id": null,
    "wikidata_id": null,
    "facebook_id": null,
    "instagram_id": "miss.scarlett.brielle",
    "tiktok_id": null,
    "twitter_id": null,
    "youtube_id": null
  }
}