{
  "adult": false,
  "also_known_as": [
    "周政杰",
    "Zhou Zheng Jie",
    "Zhengjie Zhou"
  ],
  "biography": "",
  "birthday": "2000-12-23",
  "deathday": null,
  "gender": 2,
  "homepage": null,
  "id": 4062369,
  "imdb_id": null,
  "known_for_department": "Acting",
  "name": "Zhou Zhengjie",
  "place_of_birth": "Jincheng, Shanxi, China",
  "popularity": 0.8024,
  "profile_path": "/9n4vnXt6SIrfUfDDXxz4ewxhbSf.jpg",
  "external_ids": {
    "freebase_mid": null,
    "freebase_id": null,
    "imdb_id": null,
    "tvrage_id": null,
    "wikidata_id": null,
    "facebook_id": null,
    "instagram_id": null,
    "tiktok_id": null,
    "twitter_id": null,
    "youtube_id": null
  }
}