{
  "adult": false,
  "also_known_as": [
    "아나 카스티요",
    "Anna Castillo Ferré ",
    "アンナ・カスティーリョ",
    "آنا کاستیو",
    "آنا کاستیلو"
  ],
  "biography": "",
  "birthday": "1993-10-09",
  "deathday": null,
  "gender": 1,
  "homepage": null,
  "id": 1031914,
  "imdb_id": "nm1298582",
  "known_for_department": "Acting",
  "name": "Anna Castillo",
  "place_of_birth": "Barcelona, España",
  "popularity": 2.2597,
  "profile_path": "/skQ9HzWM4Ya9YB6J9QSRPVgjfNG.jpg",
  "external_ids": {
    "freebase_mid": "/m/0_yspjn",
    "freebase_id": null,
    "imdb_id": "nm1298582",
    "tvrage_id": null,
    "wikidata_id": "Q5696237",
    "facebook_id": null,
    "instagram_id": "nanitita",
    "tiktok_id": null,
    "twitter_id": "annaacastillo",
    "youtube_id": null
  }
}