{
  "adult": false,
  "also_known_as": [
    "Eiza Gonzalez",
    "Eiza González Reyna"
  ],
  "biography": "Eiza González (born January 30, 1990) is a Mexican actress and singer. She gained popularity for her debut role as Lola Valente in the Mexican musical Lola, érase una vez. She also portrayed the lead role of Clara Molina on the Nickelodeon teen drama Sueña conmigo. She is also known for her roles as Monica \"Darling\" Castello in the action crime film Baby Driver (2017), Nyssiana in the cyberpunk action film Alita: Battle Angel (2019), Madam M in The Fast and the Furious spin-off film Hobbs & Shaw, Fran in I Care A Lot (2021).",
  "birthday": "1990-01-30",
  "deathday": null,
  "gender": 1,
  "homepage": null,
  "id": 1222992,
  "imdb_id": "nm2555462",
  "known_for_department": "Acting",
  "name": "Eiza González",
  "place_of_birth": "Mexico City, Mexico",
  "popularity": 8.0599,
  "profile_path": "/w2pZ8gLqZNguj8cqrDGbMw2Ibj0.jpg",
  "external_ids": {
    "freebase_mid": "/m/03wffhs",
    "freebase_id": "/en/eiza_gonzalez",
    "imdb_id": "nm2555462",
    "tvrage_id": null,
    "wikidata_id": "Q572761",
    "facebook_id": null,
    "instagram_id": "eizagonzalez",
    "tiktok_id": null,
    "twitter_id": "eizamusica",
    "youtube_id": "@EizaVEVO"
  }
}