{
  "adult": false,
  "also_known_as": [],
  "biography": "",
  "birthday": "1983-06-05",
  "deathday": null,
  "gender": 1,
  "homepage": null,
  "id": 105186,
  "imdb_id": "nm1908148",
  "known_for_department": "Acting",
  "name": "Челси Крисп",
  "place_of_birth": "Phoenix, Arizona, USA",
  "popularity": 0.9226,
  "profile_path": "/5sigf9eefPyVEJsAFv0DOilIle2.jpg",
  "external_ids": {
    "freebase_mid": null,
    "freebase_id": null,
    "imdb_id": "nm1908148",
    "tvrage_id": null,
    "wikidata_id": "Q20658435",
    "facebook_id": null,
    "instagram_id": null,
    "tiktok_id": null,
    "twitter_id": null,
    "youtube_id": null
  }
}