{
  "adult": false,
  "also_known_as": [
    "Thomas Pang"
  ],
  "biography": "",
  "birthday": null,
  "deathday": null,
  "gender": 2,
  "homepage": null,
  "id": 3495960,
  "imdb_id": "nm6856042",
  "known_for_department": "Acting",
  "name": "Яо",
  "place_of_birth": null,
  "popularity": 0.5235,
  "profile_path": "/hRMKy14F6zvDnwM3nRGOCVMTDmQ.jpg",
  "external_ids": {
    "freebase_mid": null,
    "freebase_id": null,
    "imdb_id": "nm6856042",
    "tvrage_id": null,
    "wikidata_id": null,
    "facebook_id": null,
    "instagram_id": "itsjustyao",
    "tiktok_id": null,
    "twitter_id": null,
    "youtube_id": null
  }
}