{
  "adult": false,
  "also_known_as": [
    "Walter Bruce Willis"
  ],
  "biography": "💥Уолтер Брюс Уиллис. Родился в 1955-ом году в Идар-Оберштайне, Германия. Рос в семье с 2-мя братьями и сестрой. Отец работал сварщиком, а мать была банковской служащей. Учился в Монтклерском государственном университете. Работает актёром и продюсером. Дважды женат: на актрисе Деми Мур (родилось 3 дочери: Румер, Скаут и Таллула) и с 2009-го на модели Эмме Хеминг, у пары 2-ое дочерей: Мэйбел и Эвелин\n\n🏆Главные награды🏆: Золотой глобус (1987) [Детективное агентство Лунный свет], Эмми (1987) [Детективное агентство Лунный свет]\n\n🎬Главные проекты🎬: «Крепкий орешек» (1988), «Криминальное чтиво» (1994), «Шестое чувство» (1999), «Детективное агентство Лунный свет» (1985), «Армагеддон» (1998), «Неуязвимый» (2000)\n\n⭐Интересный факт⭐: Брюс в детстве заикался, но сумел полностью избавиться от заикания на сцене",
  "birthday": "1955-03-19",
  "deathday": null,
  "gender": 2,
  "homepage": null,
  "id": 62,
  "imdb_id": "nm0000246",
  "known_for_department": "Acting",
  "name": "Брюс Уиллис",
  "place_of_birth": "Idar-Oberstein, West Germany [now Germany]",
  "popularity": 6.6856,
  "profile_path": "/w3aXr1e7gQCn8MSp1vW4sXHn99P.jpg",
  "external_ids": {
    "freebase_mid": "/m/0h7pj",
    "freebase_id": "/en/bruce_willis",
    "imdb_id": "nm0000246",
    "tvrage_id": 10183,
    "wikidata_id": "Q2680",
    "facebook_id": "",
    "instagram_id": null,
    "tiktok_id": null,
    "twitter_id": null,
    "youtube_id": null
  }
}