{
  "adult": false,
  "also_known_as": [
    "Anthony Kingsley Daniels"
  ],
  "biography": "Anthony Daniels (born February 21, 1946) is an English actor and mime artist, best known for playing C-3PO in 11 Star Wars films (every film of the Skywalker saga, Rogue One and The Clone Wars theatrical film). He is the only actor to have either appeared in or been involved with all theatrical films in the series, and has been involved in many of their spin-offs, including television series, video games, and radio serials.\n\nDescription above from the Wikipedia article Anthony Daniels, licensed under CC-BY-SA, full list of contributors on Wikipedia.​",
  "birthday": "1946-02-21",
  "deathday": null,
  "gender": 2,
  "homepage": "http://www.anthonydaniels.com/",
  "id": 6,
  "imdb_id": "nm0000355",
  "known_for_department": "Acting",
  "name": "Anthony Daniels",
  "place_of_birth": "Salisbury, Wiltshire, England, UK",
  "popularity": 1.9709,
  "profile_path": "/7kR4kwXtvXtvrsxWeX3QLX5NS5V.jpg",
  "external_ids": {
    "freebase_mid": "/m/02xn_q",
    "freebase_id": "/en/anthony_daniels",
    "imdb_id": "nm0000355",
    "tvrage_id": 29232,
    "wikidata_id": "Q441685",
    "facebook_id": null,
    "instagram_id": "anthonydanielsofficial",
    "tiktok_id": null,
    "twitter_id": "ADaniels3PO",
    "youtube_id": null
  }
}