{
  "adult": false,
  "also_known_as": [
    "Keegan Michael Key",
    "Key & Peele",
    "키건 마이클 키",
    "科甘-迈克尔·凯",
    "基根麥可·基",
    "کیگان-مایکل کی"
  ],
  "biography": "💥Киган-Майкл Кей. Родился в 1971-ом году в Саутфилде, Мичиган, США. Рос в семье с 2-мя братьями. Отец работал социальным работником, а мать была преподавателем. Учился в Университете Детройта и получил степень магистра в Школе драмы Пенсильванского университета. Работает актёром, комиком, сценаристом и продюсером. C 2018-го женат на продюсере Элли Шерлок, детей у пары нет\n\n🏆Главные награды🏆: Эмми (2016) [Кей и Пил], Peabody Awards (2013) [Кей и Пил], NAACP Awards (2015) [Кей и Пил]\n\n🎬Главные проекты🎬: «Кей и Пил» (2012), «Киану» (2016), «Вонка» (2023), «Братья Супер Марио в кино» (2023), «Шмигадун!» (2021)\n\n⭐Интересный факт⭐: Киган-Майкл Кей был усыновлён в младенчестве, и только во взрослом возрасте узнал, что у него есть два родных брата. Он активно выступает за развитие разнообразия и инклюзивности в киноиндустрии",
  "birthday": "1971-03-22",
  "deathday": null,
  "gender": 2,
  "homepage": null,
  "id": 298410,
  "imdb_id": "nm1221047",
  "known_for_department": "Acting",
  "name": "Киган-Майкл Кей",
  "place_of_birth": "Southfield, Michigan, USA",
  "popularity": 3.9985,
  "profile_path": "/vAR5gVXRG2Cl6WskXT99wgkAoH8.jpg",
  "external_ids": {
    "freebase_mid": "/m/0b1dys",
    "freebase_id": "/en/keegan-michael_key",
    "imdb_id": "nm1221047",
    "tvrage_id": 94292,
    "wikidata_id": "Q6382703",
    "facebook_id": "keeganmichaelkey",
    "instagram_id": "keeganmic",
    "tiktok_id": null,
    "twitter_id": "KeeganMKey",
    "youtube_id": null
  }
}