{
  "adult": false,
  "also_known_as": [],
  "biography": "Justin Burquist is an American filmmaker and music video director who directed the films Broken Knuckles (2013), Touch (2022), and was the cinematographer for the films Hemet, or the Landlady Don't Drink Tea (2023) and Pulp Friction (2021). Burquist's films have won awards at Oceanside International Film Festival and Berlin Short Film Festival.\n\nThis article uses material from the Wikipedia article \"Justin Burquist\", which is released under the Creative Commons Attribution-Share-Alike License 3.0.",
  "birthday": null,
  "deathday": null,
  "gender": 2,
  "homepage": "https://www.jburq.com/",
  "id": 1266947,
  "imdb_id": "nm3767278",
  "known_for_department": "Writing",
  "name": "Justin Burquist",
  "place_of_birth": null,
  "popularity": 0.0912,
  "profile_path": "/rzxRqtaIaspR4pC8l7bA2gPAhJe.jpg",
  "external_ids": {
    "freebase_mid": "/g/11d_vbysmr",
    "freebase_id": "",
    "imdb_id": "nm3767278",
    "tvrage_id": null,
    "wikidata_id": "Q33281968",
    "facebook_id": null,
    "instagram_id": null,
    "tiktok_id": null,
    "twitter_id": null,
    "youtube_id": null
  }
}