{
  "adult": false,
  "also_known_as": [
    "Walter Charles Dance",
    "Волтер Чарльз Денс"
  ],
  "biography": "",
  "birthday": "1946-10-10",
  "deathday": null,
  "gender": 2,
  "homepage": null,
  "id": 4391,
  "imdb_id": "nm0001097",
  "known_for_department": "Acting",
  "name": "Чарльз Дэнс",
  "place_of_birth": "Redditch, Worcestershire, England, UK",
  "popularity": 4.0649,
  "profile_path": "/3xHwq5lchAI6mfW0aGQOEijexv6.jpg",
  "external_ids": {
    "freebase_mid": "/m/06j8wx",
    "freebase_id": "/en/charles_dance",
    "imdb_id": "nm0001097",
    "tvrage_id": 81300,
    "wikidata_id": "Q309690",
    "facebook_id": null,
    "instagram_id": null,
    "tiktok_id": null,
    "twitter_id": null,
    "youtube_id": null
  }
}