{
  "adult": false,
  "also_known_as": [
    "Zlatko Buric",
    "زلاتکو بوریچ"
  ],
  "biography": "💥Златко Бурич. Родился в 1953-ем году в Осеке, Югославия. Рос в семье с младшим братом. Отец работал инженером, а мать была домохозяйкой. Учился в Академии драматического искусства в Загребе. Работает актёром. Дважды женат: на Соне Хиндкьер (родилось 3-ое детей, имена и пол, которых, не раскрывается) и с 1998-го на актрисе Драгане Милутинович, детей у пары нет\n\n🏆Главные награды🏆: Европейская киноакадемия (2022) [Треугольник печали]\n\n🎬Главные проекты🎬: «Треугольник печали» (2022), «Дилер» (1996), «2012» (2009), «Супермен» (2025), «Чудо-человек» (2026)\n\n⭐Интересный факт⭐: Златко часто играет харизматичных криминальных персонажей",
  "birthday": "1953-05-13",
  "deathday": null,
  "gender": 2,
  "homepage": null,
  "id": 31960,
  "imdb_id": "nm0121519",
  "known_for_department": "Acting",
  "name": "Златко Бурич",
  "place_of_birth": "Osijek, Croatia",
  "popularity": 2.0563,
  "profile_path": "/2b9ErKvUwblnByewNMXqBtFEIzQ.jpg",
  "external_ids": {
    "freebase_mid": null,
    "freebase_id": null,
    "imdb_id": "nm0121519",
    "tvrage_id": null,
    "wikidata_id": "Q207149",
    "facebook_id": null,
    "instagram_id": null,
    "tiktok_id": null,
    "twitter_id": null,
    "youtube_id": null
  }
}