{
  "adult": false,
  "also_known_as": [
    "Рик Роман Во",
    "Ric Waugh",
    "리크 로만 보우",
    "里克·罗曼·沃夫"
  ],
  "biography": "Ric Roman Waugh (born February 20, 1968) is an American film director, writer, producer, actor, and former stuntman. He is known for his work in Felon (2008), Snitch (2013), and Shot Caller (2017). He wrote and directed Angel Has Fallen (2019), the third instalment in the Has Fallen series.\n\nHe is the older brother of director Scott Waugh.\n\nDescription above from the Wikipedia article Ric Roman Waugh, licensed under CC-BY-SA, is a full list of contributors on Wikipedia.",
  "birthday": "1968-02-20",
  "deathday": null,
  "gender": 2,
  "homepage": null,
  "id": 76422,
  "imdb_id": "nm0006846",
  "known_for_department": "Directing",
  "name": "Ric Roman Waugh",
  "place_of_birth": "Los Angeles, California, USA",
  "popularity": 1.2334,
  "profile_path": "/cu0MJd4exIgSLgaE0uwMDTFQcpA.jpg",
  "external_ids": {
    "freebase_mid": null,
    "freebase_id": null,
    "imdb_id": "nm0006846",
    "tvrage_id": null,
    "wikidata_id": "Q23697700",
    "facebook_id": null,
    "instagram_id": null,
    "tiktok_id": null,
    "twitter_id": null,
    "youtube_id": null
  }
}