{
  "adult": false,
  "also_known_as": [],
  "biography": "Katherine Esther Jackson is the mother of famous musicians including Michael and Janet Jackson, and is known as the matriarch of the Jackson family. A talented musician herself, Katherine played the clarinet and piano, and sang.",
  "birthday": "1930-05-04",
  "deathday": null,
  "gender": 1,
  "homepage": null,
  "id": 1137185,
  "imdb_id": "nm1808277",
  "known_for_department": "Acting",
  "name": "Katherine Jackson",
  "place_of_birth": null,
  "popularity": 0.2935,
  "profile_path": "/q88gKJ0VfGv1CJrkG4maB82BH0k.jpg",
  "external_ids": {
    "freebase_mid": null,
    "freebase_id": null,
    "imdb_id": "nm1808277",
    "tvrage_id": null,
    "wikidata_id": "Q238402",
    "facebook_id": null,
    "instagram_id": null,
    "tiktok_id": null,
    "twitter_id": null,
    "youtube_id": null
  }
}