{
  "adult": false,
  "also_known_as": [
    "Reynaldo Mazzei"
  ],
  "biography": "Humberto Duarte Mauro (30 April 1897 – 5 October 1983) was a Brazilian film director. He is often considered the greatest director of early Brazilian cinema.\n\nMauro's second feature film Thesouro Perdido (Lost Treasure) won the Brazilian \"Film of the Year\" award in 1927. Later that year, Phebo Sul America Film was reorganized into Phebo Brasil Film. The first film released under the new Phebo was Braza Dormida (Sleeping Ember). Braza Dormida was a boxoffice success and furthered Mauro's career as one of Brazil's leading directors.\n\nIn July 1929, Mauro's final film for Phebo Brasil Film, Sangue Mineiro (Blood of Minas Gerais), was shown in Cataguases. In 1930, the film was given a nationwide release. The film was critically and popularly acclaimed. This was the first film in which Mauro worked with Carmen Santos who would star in many of Mauro's later films.\n\nPhebo Brasil Film did not have the resources to continue to produce films. Adhemar Gonzaga offered Mauro a directing job for Cinédia, which was centered in Rio de Janeiro. Gonzaga had started to shoot Lábios sem Beijos (Lips Without Kisses) which starred Carmen Santos. However, Carmen became pregnant was unable to finish production. Gonzaga handed the project over to Mauro, who both directed and photograpghed the film, in March 1930. Mauro decided to make the film silent even though sound was available. He wanted to explore the possibilities of silent film. Upon release in 1930, the film won the Jornal do Brasil film of the year award. Mauro acted as cinematographer for Cinédia's second film Muhler (Woman).\n\nMauro began shooting Ganga Bruta in September 1931. The film was not completed until 1933 due to cast replacements. The film was silent with synchronized sound recorded on Vitaphone discs added later. The film received little acclaim until two decades after its release.\n\nMauro co-directed his first talking film with Adhemar Gonzaga. A Voz do Carnaval (The Voice of Carnival) was a musical. Afterwards, Mauro left Cinédia for Brasil Vita Filme in 1934. He directed two feature films and several documentaries for Brasil Vita Filme.\n\nIn 1936, Mauro joined the Instituto de Nacional do Cinema Educativo (INCE), which was then the government office for educational and propaganda films. Mauro shot hundreds of documentaries when he was working in INCE, and he also shot his last three movies: Descobrimento do Brasil (The Discovery of Brazil), Argila (Clay), and O Canto da Saudade (The Song of Yearning). His final film was Carro de Bois (Ox Cart), a documentary, in 1974.\n\nDescription above from the Wikipedia article Humberto Mauro, full list of contributors on Wikipedia.",
  "birthday": "1897-04-30",
  "deathday": "1983-11-05",
  "gender": 2,
  "homepage": null,
  "id": 1088239,
  "imdb_id": "nm0561230",
  "known_for_department": "Directing",
  "name": "Humberto Mauro",
  "place_of_birth": "Volta Grande, Minas Gerais, Brazil",
  "popularity": 0.1123,
  "profile_path": "/lPgeWkbKid3n7xVPCNbQCIfipiY.jpg",
  "external_ids": {
    "freebase_mid": null,
    "freebase_id": null,
    "imdb_id": "nm0561230",
    "tvrage_id": null,
    "wikidata_id": "Q981968",
    "facebook_id": null,
    "instagram_id": null,
    "tiktok_id": null,
    "twitter_id": null,
    "youtube_id": null
  }
}