{
  "adult": false,
  "also_known_as": [
    "John Charlie Johns",
    "جانکارلو جانینی"
  ],
  "biography": "Giancarlo Giannini (Italian: [dʒaŋˈkarlo dʒanˈniːni]; born 1 August 1942) is an Italian actor. He won the Cannes Film Festival Award for Best Actor for his performance in Love and Anarchy (1973) and received an Academy Award nomination for Seven Beauties (1975). He is also a four-time recipient of the David di Donatello Award for Best Actor.\n\nGiannini began his career on stage, starring in Franco Zeffirelli's productions of Romeo and Juliet and A Midsummer Night's Dream. After appearing predominantly on television throughout the early 1960s, he had his first lead role in a film in Rita the Mosquito (1965), the first of many collaborations with filmmaker Lina Wertmüller. He rose to international stardom through Wertmüller's The Seduction of Mimi (1972), Love and Anarchy (1973), Swept Away (1974), culminating in his Oscar-nominated turn in Seven Beauties (1975).\n\nHis other films include The Innocent (1976), Lili Marleen (1980), New York Stories (1990), A Walk in the Clouds (1995), Hannibal (2001), Man on Fire (2004), and the James Bond films Casino Royale (2006) and Quantum of Solace (2008). He is also a dubbing artist, contributing voice work to the Italian-language versions of dozens of films since the 1960s. He has been the main Italian dubber of Al Pacino since 1975, and has also dubbed Jack Nicholson, Michael Douglas, and Helmut Berger.\n\nDescription above from the Wikipedia article Giancarlo Giannini, licensed under CC-BY-SA, full list of contributors on Wikipedia.",
  "birthday": "1942-08-01",
  "deathday": null,
  "gender": 2,
  "homepage": null,
  "id": 3753,
  "imdb_id": "nm0316284",
  "known_for_department": "Acting",
  "name": "Giancarlo Giannini",
  "place_of_birth": "La Spezia, Liguria, Italy",
  "popularity": 1.6666,
  "profile_path": "/xsnoThKUjFlhmvXKS4ZqAx1x3zb.jpg",
  "external_ids": {
    "freebase_mid": "/m/015qzv",
    "freebase_id": "/en/giancarlo_giannini",
    "imdb_id": "nm0316284",
    "tvrage_id": 116437,
    "wikidata_id": "Q315258",
    "facebook_id": null,
    "instagram_id": null,
    "tiktok_id": null,
    "twitter_id": null,
    "youtube_id": null
  }
}