{
  "adult": false,
  "also_known_as": [
    "Nicholas King \"Nick\" Nolte",
    "Nicholas King Nolte"
  ],
  "biography": "Ник Нолти\n\nАмериканский актёр, трёхкратный номинант на премию «Оскар» (1992, 1999, 2012), номинант на премию «Эмми» (1977), лауреат премии «Золотой глобус» (1992).\n\nНаиболее примечательные фильмы с участием Ника Нолти — «Сорок восемь часов» (1982), «Нью-йоркские истории» (1989), «Мыс страха» (1991), «Повелитель приливов» (1991), «Масло Лоренцо» (1992), «Тонкая красная линия» (1998), «Халк» (2003), «Отель „Руанда“» (2004), «Париж, я люблю тебя» (2006), «Мирный воин» (2006), «Солдаты неудачи» (2008) «Воин» (2011) , Падре (фильм, 2018).\n\nНик Нолти (урождённый Николас Кинг Нолти) родился 8 февраля 1941 года в Омахе (штат Небраска) в семье Хелен Кинг, владелицы супермаркета, и её мужа Фрэнклина Артура Нолти, бывшего футболиста. Дед Ника по отцу имел немецкие корни. Вместе с Ником росла и старшая сестра Нэнси, ставшая впоследствии сотрудником Международного движения Красного Креста и Красного Полумесяца.\n\nНолти окончил Вестсайдскую среднюю школу в Омахе, где был членом местной футбольной команды. Во время учёбы в колледже Пасадена-Сити (англ.)русск., который он окончил в 1965 году, Нолти работал на пивоваренной компании Falstaff Brewing Corporation. Пройдя актёрские курсы в нескольких академиях, Нолти работал в небольших театрах.\n\nДебют Нолти в большом кино состоялся в 1973 году, с выходом на экраны приключенческого боевика Джеймса Уильяма Гуэрчио (англ.)русск. «Парни в синей форме (англ.)русск.», где актёр исполнил эпизодическую роль молодого хиппи. В 1977 году Нолти номинировался на премии «Золотой глобус» и «Эмми» за роль Тома Йордаше в мини-сериале «Богач, бедняк (англ.)русск.». Роль, прославившая его на весь мир — сержант Джек Кейтс в триллере Уолтера Хилла «Сорок восемь часов» (1982), где его партнёром был Эдди Мёрфи.\n\nАктёр стал обладателем «Золотого глобуса» в 1992 году, за перевоплощение в неудачника Тома Уинго в мелодраме Барбры Стрейзанд «Повелитель приливов»[5]. За эту же роль Нолти впервые номинировался на премию «Оскар», но проиграл Энтони Хопкинсу. Позже Нолти ещё два раза выдвигался на «Оскар»: в 1998 году за роль Уэйда Уайтхауса в драме «Скорбь» и в 2012 году за роль Пэдди Конлона в спортивной драме «Воин».",
  "birthday": "1941-02-08",
  "deathday": null,
  "gender": 2,
  "homepage": null,
  "id": 1733,
  "imdb_id": "nm0000560",
  "known_for_department": "Acting",
  "name": "Ник Нолти",
  "place_of_birth": "Omaha, Nebraska, USA",
  "popularity": 3.352,
  "profile_path": "/jpYzFBi6zfn8CHVaXmqgiOTas4V.jpg",
  "external_ids": {
    "freebase_mid": "/m/0lkr7",
    "freebase_id": "/en/nick_nolte",
    "imdb_id": "nm0000560",
    "tvrage_id": 87436,
    "wikidata_id": "Q188018",
    "facebook_id": null,
    "instagram_id": null,
    "tiktok_id": null,
    "twitter_id": null,
    "youtube_id": null
  }
}