{
  "adult": false,
  "also_known_as": [
    "Emba",
    "Emma Frances Chamberlain"
  ],
  "biography": "Emma Frances Chamberlain (born May 22, 2001) is an American internet personality, YouTuber, podcaster and model. She won the 2018 Streamy Award for Breakout Creator. In 2019, Time magazine included her on its Time 100 Next list, and its list of The 25 Most Influential People On The Internet, writing that \"Chamberlain pioneered an approach to vlogging that shook up YouTube's unofficial style guide.\" In April 2019, she launched her first weekly podcast series, Anything Goes, formerly known as Stupid Genius. Chamberlain subsequently won the award for \"Best Podcaster\" at the 12th Shorty Awards. She also has been an ambassador for Louis Vuitton since 2019 and Cartier since 2022.",
  "birthday": "2001-05-22",
  "deathday": null,
  "gender": 1,
  "homepage": null,
  "id": 2741137,
  "imdb_id": "nm10524027",
  "known_for_department": "Acting",
  "name": "Emma Chamberlain",
  "place_of_birth": "San Bruno, California, USA",
  "popularity": 0.8888,
  "profile_path": "/qNvP5UNkidWuQwLZijX7En1NJwe.jpg",
  "external_ids": {
    "freebase_mid": null,
    "freebase_id": null,
    "imdb_id": "nm10524027",
    "tvrage_id": null,
    "wikidata_id": "Q63349606",
    "facebook_id": null,
    "instagram_id": "emmachamberlain",
    "tiktok_id": null,
    "twitter_id": "emmachamberlain",
    "youtube_id": "@emmachamberlain"
  }
}