{
  "adult": false,
  "also_known_as": [
    "Uma Karuna Thurman"
  ],
  "biography": "💥Ума Каруна Турман. Родилась в 1970-ом году в Бостоне, Массачусетс, США. Росла в семье с 2-мя братьями и младшей сестрой. Отец работал профессором, а мать была моделью. Училась в средней школе Патни в Вермонте. Работает актрисой и продюсером. Была замужем за актёром Гэри Олдманом, за актёром Итаном Хоуком (родилась дочь Майя и сын Левон). Состояла в отношениях с финансистом Арпадом Бюссоном (родилась дочь Розалинд). Свою текущую личную жизнь предпочитает держать в тайне\n\n🏆Главные награды🏆: Золотой глобус (2003) [Истерическая слепота], Номинация на Оскар (1995) [Криминальное чтиво], Номинация на BAFTA (1995) [Криминальное чтиво]\n\n🎬Главные проекты🎬: «Криминальное чтиво» (1994), «Убить Билла» (2003), «Гаттака» (1997), «Опасные связи» (1988), «Бэтмен и Робин» (1997), «Нимфоманка» (2013)\n\n⭐Интересный факт⭐: Ума получила имя в честь индуистской богини",
  "birthday": "1970-04-29",
  "deathday": null,
  "gender": 1,
  "homepage": null,
  "id": 139,
  "imdb_id": "nm0000235",
  "known_for_department": "Acting",
  "name": "Ума Турман",
  "place_of_birth": "Boston, Massachusetts, USA",
  "popularity": 10.1827,
  "profile_path": "/sBgAZWi3o4FsnaTvnTNtK6jpQcF.jpg",
  "external_ids": {
    "freebase_mid": "/m/0kjrx",
    "freebase_id": "/en/uma_thurman",
    "imdb_id": "nm0000235",
    "tvrage_id": 59413,
    "wikidata_id": "Q125017",
    "facebook_id": "umathurman",
    "instagram_id": "umathurman",
    "tiktok_id": null,
    "twitter_id": "umathurman",
    "youtube_id": null
  }
}